<!--
************ Estándar ************
Fecha/Hora.: 22/02/22 14:16:29
Usuario....: Ricardo Coulthurst (1)
Version XML: 5 

Cuenta.....: DE-1 SAAVEDRA BALLESTA NOELIA NEMESIS NEMESIS
Fantasia...: NEMESIS
Direccion..: CHUCARRO 1146  (POCITOS,MONTEVIDEO)
T.Comercio.: 1 COMERCIO COMUN
Actividad..: 13 PELUQUERIA ESTETICA SPA

Terminal...: 30200001 ES 20/09/17 11:14
PTID.......: 74196598
NroSerie...: 261-959-275 VX520
Contrato...: OCA: Ninguna             
-->
<Inicializacion>
	<BaseGeneral>
		<ipInicializa1>200.058.130.206</ipInicializa1>
		<ipInicializa2>200.058.130.206</ipInicializa2>
		<puertoInicializa1>30402</puertoInicializa1>
		<puertoInicializa2>30402</puertoInicializa2>
		<telInicializa1>22024848</telInicializa1>
		<telInicializa2>22024848</telInicializa2>
	</BaseGeneral>
	<dld>
		<variable>
			<grupo>1</grupo>
			<nombreVariable>*CHECKSCRIPT</nombreVariable>
			<valor>ON</valor>
		</variable>
		<variable>
			<grupo>1</grupo>
			<nombreVariable>*FLUJOAONOFF</nombreVariable>
			<valor>ON</valor>
		</variable>
		<variable>
			<grupo>1</grupo>
			<nombreVariable>*FLUJOB</nombreVariable>
			<valor>B</valor>
		</variable>
		<variable>
			<grupo>1</grupo>
			<nombreVariable>*REMOTE_PACKAGE_ZIP</nombreVariable>
			<valor>PAQUETES/PACKAGE.ZIP</valor>
		</variable>
		<variable>
			<grupo>1</grupo>
			<nombreVariable>*RUTA_COMANDO</nombreVariable>
			<valor>COMANDOS/</valor>
		</variable>
		<variable>
			<grupo>1</grupo>
			<nombreVariable>*CONCILIACION</nombreVariable>
			<valor>NO</valor>
		</variable>
		<variable>
			<grupo>1</grupo>
			<nombreVariable>MODO</nombreVariable>
			<valor>COMUN</valor>
		</variable>
		<variable>
			<grupo>1</grupo>
			<nombreVariable>*IP_ITD</nombreVariable>
			<valor>200.058.130.206</valor>
		</variable>
		<variable>
			<grupo>1</grupo>
			<nombreVariable>*PUERTO_ITD</nombreVariable>
			<valor>30424</valor>
		</variable>
		<variable>
			<grupo>1</grupo>
			<nombreVariable>*ITD_SIEMPRE</nombreVariable>
			<valor>N</valor>
		</variable>
		<variable>
			<grupo>1</grupo>
			<nombreVariable>*ITD_INTERVALO</nombreVariable>
			<valor>10000</valor>
		</variable>
		<variable>
			<grupo>1</grupo>
			<nombreVariable>*TLS_ITD</nombreVariable>
			<valor>N</valor>
		</variable>
		<variable>
			<grupo>1</grupo>
			<nombreVariable>CTLS_FFF5_PESOS</nombreVariable>
			<valor>000000100000</valor>
		</variable>
		<variable>
			<grupo>1</grupo>
			<nombreVariable>CTLS_FFF5_DOLARES</nombreVariable>
			<valor>000000002500</valor>
		</variable>
	</dld>
	<BaseBin>
		<Bin>
			<!--***** OCA S.A./OCA *******-->
			<idBin>1</idBin>
			<idAdquirente>3</idAdquirente>
			<nombreSello>OCA</nombreSello>
			<colBines>
				<rangoBin>
					<binDesde>589892</binDesde>
					<binHasta>589892</binHasta>
					<rangoExtDesde>000</rangoExtDesde>
					<rangoExtHasta>999</rangoExtHasta>
				</rangoBin>
				<rangoBin>
					<binDesde>542991</binDesde>
					<binHasta>542991</binHasta>
					<rangoExtDesde>000</rangoExtDesde>
					<rangoExtHasta>999</rangoExtHasta>
				</rangoBin>
				<rangoBin>
					<binDesde>549530</binDesde>
					<binHasta>549530</binHasta>
					<rangoExtDesde>000</rangoExtDesde>
					<rangoExtHasta>999</rangoExtHasta>
				</rangoBin>
				<rangoBin>
					<binDesde>549564</binDesde>
					<binHasta>549564</binHasta>
					<rangoExtDesde>000</rangoExtDesde>
					<rangoExtHasta>999</rangoExtHasta>
				</rangoBin>
				<rangoBin>
					<binDesde>549571</binDesde>
					<binHasta>549571</binHasta>
					<rangoExtDesde>000</rangoExtDesde>
					<rangoExtHasta>999</rangoExtHasta>
				</rangoBin>
				<rangoBin>
					<binDesde>549576</binDesde>
					<binHasta>549576</binHasta>
					<rangoExtDesde>000</rangoExtDesde>
					<rangoExtHasta>999</rangoExtHasta>
				</rangoBin>
				<rangoBin>
					<binDesde>589107</binDesde>
					<binHasta>589107</binHasta>
					<rangoExtDesde>000</rangoExtDesde>
					<rangoExtHasta>999</rangoExtHasta>
				</rangoBin>
			</colBines>
			<DL_FAST_CO>false</DL_FAST_CO>
			<DL_SDLCINT>ATW2X4S25=1&amp;D2%C0\N0+A8E=,,,1</DL_SDLCINT>
			<DL_SDLC_MOD>AT+MS=V22,0,300,1200,300,1200</DL_SDLC_MOD>
			<DL_SDLC_ON>true</DL_SDLC_ON>
			<DL_START>AT&amp;FE0Q0V0</DL_START>
			<afamSC>120</afamSC>
			<cifraCanalTLS>S</cifraCanalTLS>
			<colBinesAfam>589107-589107</colBinesAfam>
			<discretionaryAfam>0</discretionaryAfam>
			<iP>200.058.130.206</iP>
			<iP2>200.058.130.206</iP2>
			<iP3>200.058.130.206</iP3>
			<impCierreTotalesCero>N</impCierreTotalesCero>
			<ksi>000002</ksi>
			<largoBinesAfam>6</largoBinesAfam>
			<location>2</location>
			<msDukpt>D</msDukpt>
			<msgInicializacion>N</msgInicializacion>
			<nIi>0009</nIi>
			<operaCredito>L</operaCredito>
			<operaDebito>N</operaDebito>
			<operaOffLine>S</operaOffLine>
			<puerto>30206</puerto>
			<puerto2>30206</puerto2>
			<puerto3>30206</puerto3>
			<requiereCuotas>S</requiereCuotas>
			<requierePIN>N</requierePIN>
			<reversaDiferida>S</reversaDiferida>
			<telnac1>28484666</telnac1>
			<telnac2>24024936</telnac2>
			<telnac3>24024936</telnac3>
			<versionEMV>2</versionEMV>
		</Bin>
		<Bin>
			<!--***** VISANET/VISA *******-->
			<idBin>2</idBin>
			<idAdquirente>4</idAdquirente>
			<nombreSello>VISA</nombreSello>
			<colBines>
				<rangoBin>
					<binDesde>400000</binDesde>
					<binHasta>499999</binHasta>
					<rangoExtDesde>000</rangoExtDesde>
					<rangoExtHasta>999</rangoExtHasta>
				</rangoBin>
			</colBines>
			<DL_FAST_CO>false</DL_FAST_CO>
			<DL_SDLCINT>ATW2X4S25=1&amp;D2%C0\N0+A8E=,,,1</DL_SDLCINT>
			<DL_SDLC_MOD>AT+MS=V22,0,300,1200,300,1200</DL_SDLC_MOD>
			<DL_SDLC_ON>true</DL_SDLC_ON>
			<DL_START>AT&amp;FE0Q0V0</DL_START>
			<afamSC>120</afamSC>
			<cifraCanalTLS>S</cifraCanalTLS>
			<colBinesAfam>0</colBinesAfam>
			<discretionaryAfam>59899</discretionaryAfam>
			<iP>200.058.130.206</iP>
			<iP2>200.058.130.206</iP2>
			<iP3>200.058.130.206</iP3>
			<impCierreTotalesCero>N</impCierreTotalesCero>
			<ksi>000019</ksi>
			<largoBinesAfam>0</largoBinesAfam>
			<location>0</location>
			<msDukpt>D</msDukpt>
			<msgInicializacion>N</msgInicializacion>
			<nIi>0705</nIi>
			<operaCredito>L</operaCredito>
			<operaDebito>L</operaDebito>
			<operaOffLine>N</operaOffLine>
			<puerto>30208</puerto>
			<puerto2>30208</puerto2>
			<puerto3>30208</puerto3>
			<requiereCuotas>S</requiereCuotas>
			<requierePIN>N</requierePIN>
			<reversaDiferida>S</reversaDiferida>
			<telnac1>29011005</telnac1>
			<telnac2>22019173</telnac2>
			<telnac3>22019173</telnac3>
			<versionEMV>1</versionEMV>
		</Bin>
		<Bin>
			<!--***** CABAL/CABAL CREDITO *******-->
			<idBin>7</idBin>
			<idAdquirente>1</idAdquirente>
			<nombreSello>CABAL CREDITO</nombreSello>
			<colBines>
				<rangoBin>
					<binDesde>589657</binDesde>
					<binHasta>589657</binHasta>
					<rangoExtDesde>000</rangoExtDesde>
					<rangoExtHasta>249</rangoExtHasta>
				</rangoBin>
				<rangoBin>
					<binDesde>589657</binDesde>
					<binHasta>589657</binHasta>
					<rangoExtDesde>260</rangoExtDesde>
					<rangoExtHasta>990</rangoExtHasta>
				</rangoBin>
				<rangoBin>
					<binDesde>603522</binDesde>
					<binHasta>603522</binHasta>
					<rangoExtDesde>000</rangoExtDesde>
					<rangoExtHasta>999</rangoExtHasta>
				</rangoBin>
				<rangoBin>
					<binDesde>604201</binDesde>
					<binHasta>604351</binHasta>
					<rangoExtDesde>000</rangoExtDesde>
					<rangoExtHasta>999</rangoExtHasta>
				</rangoBin>
				<rangoBin>
					<binDesde>604354</binDesde>
					<binHasta>604400</binHasta>
					<rangoExtDesde>000</rangoExtDesde>
					<rangoExtHasta>999</rangoExtHasta>
				</rangoBin>
			</colBines>
			<DL_FAST_CO>true</DL_FAST_CO>
			<DL_SDLCINT>ATW2X4S25=1&amp;D2%C0\N0+A8E=,,,1</DL_SDLCINT>
			<DL_SDLC_MOD>AT+MS=V22,0,300,1200,300,1200</DL_SDLC_MOD>
			<DL_SDLC_ON>true</DL_SDLC_ON>
			<DL_START>AT&amp;FE0Q0V0</DL_START>
			<afamSC>120</afamSC>
			<cifraCanalTLS>S</cifraCanalTLS>
			<colBinesAfam>0</colBinesAfam>
			<discretionaryAfam>0</discretionaryAfam>
			<iP>200.058.130.206</iP>
			<iP2>200.058.130.206</iP2>
			<iP3>200.058.130.206</iP3>
			<impCierreTotalesCero>N</impCierreTotalesCero>
			<ksi>000000</ksi>
			<largoBinesAfam>0</largoBinesAfam>
			<location>4</location>
			<msDukpt>M</msDukpt>
			<msgInicializacion>N</msgInicializacion>
			<nIi>0101</nIi>
			<operaCredito>L</operaCredito>
			<operaDebito>N</operaDebito>
			<operaOffLine>S</operaOffLine>
			<puerto>30202</puerto>
			<puerto2>30202</puerto2>
			<puerto3>30202</puerto3>
			<requiereCuotas>S</requiereCuotas>
			<requierePIN>N</requierePIN>
			<reversaDiferida>S</reversaDiferida>
			<telnac1>24878460</telnac1>
			<telnac2>24878460</telnac2>
			<telnac3>24878460</telnac3>
			<versionEMV>0</versionEMV>
		</Bin>
		<Bin>
			<!--***** EDENRED/CABAL EDENRED *******-->
			<idBin>8</idBin>
			<idAdquirente>21</idAdquirente>
			<nombreSello>CABAL EDENRED</nombreSello>
			<colBines>
				<rangoBin>
					<binDesde>637483</binDesde>
					<binHasta>637483</binHasta>
					<rangoExtDesde>000</rangoExtDesde>
					<rangoExtHasta>099</rangoExtHasta>
				</rangoBin>
				<rangoBin>
					<binDesde>637483</binDesde>
					<binHasta>637483</binHasta>
					<rangoExtDesde>100</rangoExtDesde>
					<rangoExtHasta>199</rangoExtHasta>
				</rangoBin>
				<rangoBin>
					<binDesde>637483</binDesde>
					<binHasta>637483</binHasta>
					<rangoExtDesde>200</rangoExtDesde>
					<rangoExtHasta>999</rangoExtHasta>
				</rangoBin>
			</colBines>
			<DL_FAST_CO>true</DL_FAST_CO>
			<DL_SDLCINT>ATW2X4S25=1&amp;D2%C0\N0+A8E=,,,1</DL_SDLCINT>
			<DL_SDLC_MOD>AT+MS=V22,0,300,1200,300,1200</DL_SDLC_MOD>
			<DL_SDLC_ON>true</DL_SDLC_ON>
			<DL_START>AT&amp;FE0Q0V0</DL_START>
			<afamSC>120</afamSC>
			<cifraCanalTLS>S</cifraCanalTLS>
			<colBinesAfam>0</colBinesAfam>
			<discretionaryAfam>0</discretionaryAfam>
			<iP>200.058.130.206</iP>
			<iP2>200.058.130.206</iP2>
			<iP3>200.058.130.206</iP3>
			<impCierreTotalesCero>N</impCierreTotalesCero>
			<ksi>000000</ksi>
			<largoBinesAfam>0</largoBinesAfam>
			<location>4</location>
			<msDukpt>M</msDukpt>
			<msgInicializacion>N</msgInicializacion>
			<nIi>0033</nIi>
			<operaCredito>N</operaCredito>
			<operaDebito>L</operaDebito>
			<operaOffLine>N</operaOffLine>
			<puerto>30202</puerto>
			<puerto2>30202</puerto2>
			<puerto3>30202</puerto3>
			<requiereCuotas>N</requiereCuotas>
			<requierePIN>S</requierePIN>
			<reversaDiferida>S</reversaDiferida>
			<telnac1>24878460</telnac1>
			<telnac2>24878460</telnac2>
			<telnac3>24878460</telnac3>
			<versionEMV>0</versionEMV>
		</Bin>
		<Bin>
			<!--***** CLUB DEL ESTE/CLUB DEL ESTE *******-->
			<idBin>14</idBin>
			<idAdquirente>14</idAdquirente>
			<nombreSello>CLUB DEL ESTE</nombreSello>
			<colBines>
				<rangoBin>
					<binDesde>504736</binDesde>
					<binHasta>504736</binHasta>
					<rangoExtDesde>000</rangoExtDesde>
					<rangoExtHasta>999</rangoExtHasta>
				</rangoBin>
			</colBines>
			<DL_FAST_CO>true</DL_FAST_CO>
			<DL_SDLCINT>ATW2X4S25=1&amp;D2%C0\N0+A8E=,,,1</DL_SDLCINT>
			<DL_SDLC_MOD>AT+MS=V22,0,300,1200,300,1200</DL_SDLC_MOD>
			<DL_SDLC_ON>true</DL_SDLC_ON>
			<DL_START>AT&amp;FE0Q0V0</DL_START>
			<afamSC>120</afamSC>
			<cifraCanalTLS>S</cifraCanalTLS>
			<colBinesAfam>0</colBinesAfam>
			<discretionaryAfam>0</discretionaryAfam>
			<iP>200.058.130.206</iP>
			<iP2>200.058.130.206</iP2>
			<iP3>200.058.130.206</iP3>
			<impCierreTotalesCero>N</impCierreTotalesCero>
			<ksi>000000</ksi>
			<largoBinesAfam>0</largoBinesAfam>
			<location>0</location>
			<msDukpt>M</msDukpt>
			<msgInicializacion>N</msgInicializacion>
			<nIi>0036</nIi>
			<operaCredito>S</operaCredito>
			<operaDebito>N</operaDebito>
			<operaOffLine>N</operaOffLine>
			<puerto>30229</puerto>
			<puerto2>30229</puerto2>
			<puerto3>30229</puerto3>
			<requiereCuotas>S</requiereCuotas>
			<requierePIN>N</requierePIN>
			<reversaDiferida>S</reversaDiferida>
			<telnac1>24878460</telnac1>
			<telnac2>24878460</telnac2>
			<telnac3>24878460</telnac3>
			<versionEMV>0</versionEMV>
		</Bin>
		<Bin>
			<!--***** ANDA/ANDA *******-->
			<idBin>30</idBin>
			<idAdquirente>12</idAdquirente>
			<nombreSello>ANDA</nombreSello>
			<colBines>
				<rangoBin>
					<binDesde>603199</binDesde>
					<binHasta>603199</binHasta>
					<rangoExtDesde>000</rangoExtDesde>
					<rangoExtHasta>999</rangoExtHasta>
				</rangoBin>
			</colBines>
			<DL_FAST_CO>false</DL_FAST_CO>
			<DL_SDLCINT>ATW2X4S25=1&amp;D2%C0\N0+A8E=,,,1</DL_SDLCINT>
			<DL_SDLC_MOD>AT+MS=V22,0,300,1200,300,1200</DL_SDLC_MOD>
			<DL_SDLC_ON>true</DL_SDLC_ON>
			<DL_START>AT&amp;FE0Q0V0</DL_START>
			<afamSC>126</afamSC>
			<cifraCanalTLS>N</cifraCanalTLS>
			<colBinesAfam>0</colBinesAfam>
			<discretionaryAfam>0</discretionaryAfam>
			<iP>200.058.130.206</iP>
			<iP2>200.058.130.206</iP2>
			<iP3>200.058.130.206</iP3>
			<impCierreTotalesCero>N</impCierreTotalesCero>
			<ksi>000000</ksi>
			<largoBinesAfam>0</largoBinesAfam>
			<location>0</location>
			<msDukpt>N</msDukpt>
			<msgInicializacion>N</msgInicializacion>
			<nIi>0021</nIi>
			<operaCredito>S</operaCredito>
			<operaDebito>N</operaDebito>
			<operaOffLine>S</operaOffLine>
			<puerto>30201</puerto>
			<puerto2>30201</puerto2>
			<puerto3>30201</puerto3>
			<requiereCuotas>S</requiereCuotas>
			<requierePIN>N</requierePIN>
			<reversaDiferida>S</reversaDiferida>
			<telnac1>22024848</telnac1>
			<telnac2>22024848</telnac2>
			<telnac3>22024848</telnac3>
			<versionEMV>0</versionEMV>
		</Bin>
		<Bin>
			<!--***** AMEX/AMEX *******-->
			<idBin>37</idBin>
			<idAdquirente>5</idAdquirente>
			<nombreSello>AMEX</nombreSello>
			<colBines>
				<rangoBin>
					<binDesde>340000</binDesde>
					<binHasta>349999</binHasta>
					<rangoExtDesde>000</rangoExtDesde>
					<rangoExtHasta>999</rangoExtHasta>
				</rangoBin>
				<rangoBin>
					<binDesde>370000</binDesde>
					<binHasta>379999</binHasta>
					<rangoExtDesde>000</rangoExtDesde>
					<rangoExtHasta>999</rangoExtHasta>
				</rangoBin>
			</colBines>
			<DL_FAST_CO>false</DL_FAST_CO>
			<DL_SDLCINT>ATW2X4S25=1&amp;D2%C0\N0+A8E=,,,1</DL_SDLCINT>
			<DL_SDLC_MOD>AT+MS=V22,0,300,1200,300,1200</DL_SDLC_MOD>
			<DL_SDLC_ON>true</DL_SDLC_ON>
			<DL_START>AT&amp;FE0Q0V0</DL_START>
			<afamSC>120</afamSC>
			<cifraCanalTLS>S</cifraCanalTLS>
			<colBinesAfam>0</colBinesAfam>
			<discretionaryAfam>0</discretionaryAfam>
			<iP>200.058.130.206</iP>
			<iP2>200.058.130.206</iP2>
			<iP3>200.058.130.206</iP3>
			<impCierreTotalesCero>N</impCierreTotalesCero>
			<ksi>000000</ksi>
			<largoBinesAfam>0</largoBinesAfam>
			<location>0</location>
			<msDukpt>D</msDukpt>
			<msgInicializacion>N</msgInicializacion>
			<nIi>0553</nIi>
			<operaCredito>L</operaCredito>
			<operaDebito>N</operaDebito>
			<operaOffLine>N</operaOffLine>
			<puerto>30402</puerto>
			<puerto2>30402</puerto2>
			<puerto3>30402</puerto3>
			<requiereCuotas>S</requiereCuotas>
			<requierePIN>N</requierePIN>
			<reversaDiferida>S</reversaDiferida>
			<telnac1>22024848</telnac1>
			<telnac2>22024848</telnac2>
			<telnac3>22024848</telnac3>
			<versionEMV>0</versionEMV>
		</Bin>
		<Bin>
			<!--***** PASSCARD/PASSCARD *******-->
			<idBin>50</idBin>
			<idAdquirente>10</idAdquirente>
			<nombreSello>PASSCARD</nombreSello>
			<colBines>
				<rangoBin>
					<binDesde>628026</binDesde>
					<binHasta>628026</binHasta>
					<rangoExtDesde>000</rangoExtDesde>
					<rangoExtHasta>999</rangoExtHasta>
				</rangoBin>
			</colBines>
			<DL_FAST_CO>false</DL_FAST_CO>
			<DL_SDLCINT>ATW2X4S25=1&amp;D2%C0\N0+A8E=,,,1</DL_SDLCINT>
			<DL_SDLC_MOD>AT+MS=V22,0,300,1200,300,1200</DL_SDLC_MOD>
			<DL_SDLC_ON>true</DL_SDLC_ON>
			<DL_START>AT&amp;FE0Q0V0</DL_START>
			<afamSC>120</afamSC>
			<cifraCanalTLS>N</cifraCanalTLS>
			<colBinesAfam>0</colBinesAfam>
			<discretionaryAfam>0</discretionaryAfam>
			<iP>200.058.130.206</iP>
			<iP2>200.058.130.206</iP2>
			<iP3>200.058.130.206</iP3>
			<impCierreTotalesCero>N</impCierreTotalesCero>
			<ksi>000000</ksi>
			<largoBinesAfam>6</largoBinesAfam>
			<location>0</location>
			<msDukpt>N</msDukpt>
			<msgInicializacion>N</msgInicializacion>
			<nIi>0022</nIi>
			<operaCredito>L</operaCredito>
			<operaDebito>N</operaDebito>
			<operaOffLine>N</operaOffLine>
			<puerto>30207</puerto>
			<puerto2>30207</puerto2>
			<puerto3>30207</puerto3>
			<requiereCuotas>S</requiereCuotas>
			<requierePIN>N</requierePIN>
			<reversaDiferida>S</reversaDiferida>
			<telnac1>22024848</telnac1>
			<telnac2>22024848</telnac2>
			<telnac3>22024848</telnac3>
			<versionEMV>0</versionEMV>
		</Bin>
		<Bin>
			<!--***** CREDITOS D/TARJETA D *******-->
			<idBin>51</idBin>
			<idAdquirente>600</idAdquirente>
			<nombreSello>TARJETA D</nombreSello>
			<colBines>
				<rangoBin>
					<binDesde>601828</binDesde>
					<binHasta>601828</binHasta>
					<rangoExtDesde>000</rangoExtDesde>
					<rangoExtHasta>999</rangoExtHasta>
				</rangoBin>
			</colBines>
			<DL_FAST_CO>true</DL_FAST_CO>
			<DL_SDLCINT>ATW2X4S25=1&amp;D2%C0\N0+A8E=,,,1</DL_SDLCINT>
			<DL_SDLC_MOD>AT+MS=V22,0,300,1200,300,1200</DL_SDLC_MOD>
			<DL_SDLC_ON>true</DL_SDLC_ON>
			<DL_START>AT&amp;FE0Q0V0</DL_START>
			<afamSC>120</afamSC>
			<cifraCanalTLS>N</cifraCanalTLS>
			<colBinesAfam>0</colBinesAfam>
			<discretionaryAfam>0</discretionaryAfam>
			<iP>200.058.130.206</iP>
			<iP2>200.058.130.206</iP2>
			<iP3>200.058.130.206</iP3>
			<impCierreTotalesCero>N</impCierreTotalesCero>
			<ksi>000000</ksi>
			<largoBinesAfam>6</largoBinesAfam>
			<location>0</location>
			<msDukpt>N</msDukpt>
			<msgInicializacion>N</msgInicializacion>
			<nIi>0003</nIi>
			<operaCredito>L</operaCredito>
			<operaDebito>N</operaDebito>
			<operaOffLine>S</operaOffLine>
			<puerto>30204</puerto>
			<puerto2>30204</puerto2>
			<puerto3>30204</puerto3>
			<requiereCuotas>S</requiereCuotas>
			<requierePIN>N</requierePIN>
			<reversaDiferida>S</reversaDiferida>
			<telnac1>29169491</telnac1>
			<telnac2>29162302</telnac2>
			<telnac3>29162302</telnac3>
			<versionEMV>0</versionEMV>
		</Bin>
		<Bin>
			<!--***** MIDES/MIDES *******-->
			<idBin>70</idBin>
			<idAdquirente>13</idAdquirente>
			<nombreSello>MIDES</nombreSello>
			<colBines>
				<rangoBin>
					<binDesde>802701</binDesde>
					<binHasta>802701</binHasta>
					<rangoExtDesde>000</rangoExtDesde>
					<rangoExtHasta>999</rangoExtHasta>
				</rangoBin>
				<rangoBin>
					<binDesde>802702</binDesde>
					<binHasta>802702</binHasta>
					<rangoExtDesde>000</rangoExtDesde>
					<rangoExtHasta>999</rangoExtHasta>
				</rangoBin>
			</colBines>
			<DL_FAST_CO>false</DL_FAST_CO>
			<DL_SDLCINT>ATW2X4S25=1&amp;D2%C0\N0+A8E=,,,1</DL_SDLCINT>
			<DL_SDLC_MOD>AT+MS=V22,0,300,1200,300,1200</DL_SDLC_MOD>
			<DL_SDLC_ON>true</DL_SDLC_ON>
			<DL_START>AT&amp;FE0Q0V0</DL_START>
			<afamSC>126</afamSC>
			<cifraCanalTLS>S</cifraCanalTLS>
			<colBinesAfam>0</colBinesAfam>
			<discretionaryAfam>EEEEE</discretionaryAfam>
			<iP>200.058.130.206</iP>
			<iP2>200.058.130.206</iP2>
			<iP3>200.058.130.206</iP3>
			<impCierreTotalesCero>N</impCierreTotalesCero>
			<ksi>000000</ksi>
			<largoBinesAfam>0</largoBinesAfam>
			<location>0</location>
			<msDukpt>N</msDukpt>
			<msgInicializacion>N</msgInicializacion>
			<nIi>0334</nIi>
			<operaCredito>L</operaCredito>
			<operaDebito>L</operaDebito>
			<operaOffLine>N</operaOffLine>
			<puerto>30402</puerto>
			<puerto2>30402</puerto2>
			<puerto3>30402</puerto3>
			<requiereCuotas>N</requiereCuotas>
			<requierePIN>N</requierePIN>
			<reversaDiferida>S</reversaDiferida>
			<telnac1>22024848</telnac1>
			<telnac2>22024848</telnac2>
			<telnac3>22024848</telnac3>
			<versionEMV>0</versionEMV>
		</Bin>
		<Bin>
			<!--***** CABAL/CABAL AFAM *******-->
			<idBin>776</idBin>
			<idAdquirente>1</idAdquirente>
			<nombreSello>CABAL AFAM</nombreSello>
			<colBines>
				<rangoBin>
					<binDesde>589657</binDesde>
					<binHasta>589657</binHasta>
					<rangoExtDesde>253</rangoExtDesde>
					<rangoExtHasta>254</rangoExtHasta>
				</rangoBin>
			</colBines>
			<DL_FAST_CO>true</DL_FAST_CO>
			<DL_SDLCINT>ATW2X4S25=1&amp;D2%C0\N0+A8E=,,,1</DL_SDLCINT>
			<DL_SDLC_MOD>AT+MS=V22,0,300,1200,300,1200</DL_SDLC_MOD>
			<DL_SDLC_ON>true</DL_SDLC_ON>
			<DL_START>AT&amp;FE0Q0V0</DL_START>
			<afamSC>120</afamSC>
			<cifraCanalTLS>S</cifraCanalTLS>
			<colBinesAfam>589657-589657</colBinesAfam>
			<discretionaryAfam>0</discretionaryAfam>
			<iP>200.058.130.206</iP>
			<iP2>200.058.130.206</iP2>
			<iP3>200.058.130.206</iP3>
			<impCierreTotalesCero>N</impCierreTotalesCero>
			<ksi>000000</ksi>
			<largoBinesAfam>9</largoBinesAfam>
			<location>4</location>
			<msDukpt>M</msDukpt>
			<msgInicializacion>N</msgInicializacion>
			<nIi>0101</nIi>
			<operaCredito>N</operaCredito>
			<operaDebito>L</operaDebito>
			<operaOffLine>N</operaOffLine>
			<puerto>30202</puerto>
			<puerto2>30202</puerto2>
			<puerto3>30202</puerto3>
			<requiereCuotas>N</requiereCuotas>
			<requierePIN>N</requierePIN>
			<reversaDiferida>S</reversaDiferida>
			<telnac1>24878460</telnac1>
			<telnac2>24878460</telnac2>
			<telnac3>24878460</telnac3>
			<versionEMV>0</versionEMV>
		</Bin>
		<Bin>
			<!--***** CABAL/CABAL DEBITO *******-->
			<idBin>777</idBin>
			<idAdquirente>1</idAdquirente>
			<nombreSello>CABAL DEBITO</nombreSello>
			<colBines>
				<rangoBin>
					<binDesde>589657</binDesde>
					<binHasta>589657</binHasta>
					<rangoExtDesde>255</rangoExtDesde>
					<rangoExtHasta>259</rangoExtHasta>
				</rangoBin>
				<rangoBin>
					<binDesde>604352</binDesde>
					<binHasta>604353</binHasta>
					<rangoExtDesde>000</rangoExtDesde>
					<rangoExtHasta>999</rangoExtHasta>
				</rangoBin>
			</colBines>
			<DL_FAST_CO>true</DL_FAST_CO>
			<DL_SDLCINT>ATW2X4S25=1&amp;D2%C0\N0+A8E=,,,1</DL_SDLCINT>
			<DL_SDLC_MOD>AT+MS=V22,0,300,1200,300,1200</DL_SDLC_MOD>
			<DL_SDLC_ON>true</DL_SDLC_ON>
			<DL_START>AT&amp;FE0Q0V0</DL_START>
			<afamSC>120</afamSC>
			<cifraCanalTLS>S</cifraCanalTLS>
			<colBinesAfam>0</colBinesAfam>
			<discretionaryAfam>0</discretionaryAfam>
			<iP>200.058.130.206</iP>
			<iP2>200.058.130.206</iP2>
			<iP3>200.058.130.206</iP3>
			<impCierreTotalesCero>N</impCierreTotalesCero>
			<ksi>000000</ksi>
			<largoBinesAfam>0</largoBinesAfam>
			<location>4</location>
			<msDukpt>M</msDukpt>
			<msgInicializacion>N</msgInicializacion>
			<nIi>0101</nIi>
			<operaCredito>N</operaCredito>
			<operaDebito>L</operaDebito>
			<operaOffLine>N</operaOffLine>
			<puerto>30202</puerto>
			<puerto2>30202</puerto2>
			<puerto3>30202</puerto3>
			<requiereCuotas>N</requiereCuotas>
			<requierePIN>S</requierePIN>
			<reversaDiferida>S</reversaDiferida>
			<telnac1>24878460</telnac1>
			<telnac2>24878460</telnac2>
			<telnac3>24878460</telnac3>
			<versionEMV>0</versionEMV>
		</Bin>
		<Bin>
			<!--***** CABAL/BENEFICIOS *******-->
			<idBin>778</idBin>
			<idAdquirente>1</idAdquirente>
			<nombreSello>BENEFICIOS</nombreSello>
			<colBines>
				<rangoBin>
					<binDesde>600178</binDesde>
					<binHasta>600178</binHasta>
					<rangoExtDesde>000</rangoExtDesde>
					<rangoExtHasta>999</rangoExtHasta>
				</rangoBin>
			</colBines>
			<DL_FAST_CO>true</DL_FAST_CO>
			<DL_SDLCINT>ATW2X4S25=1&amp;D2%C0\N0+A8E=,,,1</DL_SDLCINT>
			<DL_SDLC_MOD>AT+MS=V22,0,300,1200,300,1200</DL_SDLC_MOD>
			<DL_SDLC_ON>true</DL_SDLC_ON>
			<DL_START>AT&amp;FE0Q0V0</DL_START>
			<afamSC>120</afamSC>
			<cifraCanalTLS>S</cifraCanalTLS>
			<colBinesAfam>0</colBinesAfam>
			<discretionaryAfam>0</discretionaryAfam>
			<iP>200.058.130.206</iP>
			<iP2>200.058.130.206</iP2>
			<iP3>200.058.130.206</iP3>
			<impCierreTotalesCero>N</impCierreTotalesCero>
			<ksi>000000</ksi>
			<largoBinesAfam>0</largoBinesAfam>
			<location>4</location>
			<msDukpt>M</msDukpt>
			<msgInicializacion>N</msgInicializacion>
			<nIi>0101</nIi>
			<operaCredito>L</operaCredito>
			<operaDebito>N</operaDebito>
			<operaOffLine>N</operaOffLine>
			<puerto>30202</puerto>
			<puerto2>30202</puerto2>
			<puerto3>30202</puerto3>
			<requiereCuotas>N</requiereCuotas>
			<requierePIN>N</requierePIN>
			<reversaDiferida>S</reversaDiferida>
			<telnac1>24878460</telnac1>
			<telnac2>24878460</telnac2>
			<telnac3>24878460</telnac3>
			<versionEMV>0</versionEMV>
		</Bin>
		<Bin>
			<!--***** CREDITEL/CREDITEL *******-->
			<idBin>800</idBin>
			<idAdquirente>11</idAdquirente>
			<nombreSello>CREDITEL</nombreSello>
			<colBines>
				<rangoBin>
					<binDesde>601933</binDesde>
					<binHasta>601933</binHasta>
					<rangoExtDesde>000</rangoExtDesde>
					<rangoExtHasta>999</rangoExtHasta>
				</rangoBin>
			</colBines>
			<DL_FAST_CO>false</DL_FAST_CO>
			<DL_SDLCINT>ATW2X4S25=1&amp;D2%C0\N0+A8E=,,,1</DL_SDLCINT>
			<DL_SDLC_MOD>AT+MS=V22,0,300,1200,300,1200</DL_SDLC_MOD>
			<DL_SDLC_ON>true</DL_SDLC_ON>
			<DL_START>AT&amp;FE0Q0V0</DL_START>
			<afamSC>120</afamSC>
			<cifraCanalTLS>S</cifraCanalTLS>
			<colBinesAfam>0</colBinesAfam>
			<discretionaryAfam>0</discretionaryAfam>
			<iP>200.058.130.206</iP>
			<iP2>200.058.130.206</iP2>
			<iP3>200.058.130.206</iP3>
			<impCierreTotalesCero>N</impCierreTotalesCero>
			<ksi>000000</ksi>
			<largoBinesAfam>6</largoBinesAfam>
			<location>0</location>
			<msDukpt>N</msDukpt>
			<msgInicializacion>N</msgInicializacion>
			<nIi>0023</nIi>
			<operaCredito>S</operaCredito>
			<operaDebito>N</operaDebito>
			<operaOffLine>S</operaOffLine>
			<puerto>30402</puerto>
			<puerto2>30402</puerto2>
			<puerto3>30402</puerto3>
			<requiereCuotas>S</requiereCuotas>
			<requierePIN>N</requierePIN>
			<reversaDiferida>S</reversaDiferida>
			<telnac1>22024848</telnac1>
			<telnac2>22024848</telnac2>
			<telnac3>22024848</telnac3>
			<versionEMV>0</versionEMV>
		</Bin>
		<Bin>
			<!--***** FISERV/LIDER *******-->
			<idBin>101</idBin>
			<idAdquirente>2</idAdquirente>
			<nombreSello>LIDER</nombreSello>
			<colBines>
				<rangoBin>
					<binDesde>501090</binDesde>
					<binHasta>501109</binHasta>
					<rangoExtDesde>000</rangoExtDesde>
					<rangoExtHasta>999</rangoExtHasta>
				</rangoBin>
				<rangoBin>
					<binDesde>501093</binDesde>
					<binHasta>501094</binHasta>
					<rangoExtDesde>000</rangoExtDesde>
					<rangoExtHasta>999</rangoExtHasta>
				</rangoBin>
				<rangoBin>
					<binDesde>501096</binDesde>
					<binHasta>501104</binHasta>
					<rangoExtDesde>000</rangoExtDesde>
					<rangoExtHasta>999</rangoExtHasta>
				</rangoBin>
				<rangoBin>
					<binDesde>501107</binDesde>
					<binHasta>501107</binHasta>
					<rangoExtDesde>000</rangoExtDesde>
					<rangoExtHasta>999</rangoExtHasta>
				</rangoBin>
				<rangoBin>
					<binDesde>501109</binDesde>
					<binHasta>501109</binHasta>
					<rangoExtDesde>000</rangoExtDesde>
					<rangoExtHasta>999</rangoExtHasta>
				</rangoBin>
				<rangoBin>
					<binDesde>505866</binDesde>
					<binHasta>505872</binHasta>
					<rangoExtDesde>000</rangoExtDesde>
					<rangoExtHasta>999</rangoExtHasta>
				</rangoBin>
			</colBines>
			<DL_FAST_CO>false</DL_FAST_CO>
			<DL_SDLCINT>ATW2X4S25=1&amp;D2%C0\N0+A8E=,,,1</DL_SDLCINT>
			<DL_SDLC_MOD>AT+MS=V22,0,300,1200,300,1200</DL_SDLC_MOD>
			<DL_SDLC_ON>true</DL_SDLC_ON>
			<DL_START>AT&amp;FE0Q0V0</DL_START>
			<afamSC>120</afamSC>
			<cifraCanalTLS>S</cifraCanalTLS>
			<colBinesAfam>0</colBinesAfam>
			<discretionaryAfam>0</discretionaryAfam>
			<iP>200.058.130.206</iP>
			<iP2>200.058.130.206</iP2>
			<iP3>200.058.130.206</iP3>
			<impCierreTotalesCero>N</impCierreTotalesCero>
			<ksi>0B0117</ksi>
			<largoBinesAfam>0</largoBinesAfam>
			<location>1</location>
			<msDukpt>D</msDukpt>
			<msgInicializacion>N</msgInicializacion>
			<nIi>0003</nIi>
			<operaCredito>L</operaCredito>
			<operaDebito>L</operaDebito>
			<operaOffLine>N</operaOffLine>
			<puerto>30215</puerto>
			<puerto2>30205</puerto2>
			<puerto3>30215</puerto3>
			<requiereCuotas>S</requiereCuotas>
			<requierePIN>N</requierePIN>
			<reversaDiferida>S</reversaDiferida>
			<telnac1>29031239</telnac1>
			<telnac2>22015946</telnac2>
			<telnac3>22015946</telnac3>
			<versionEMV>1</versionEMV>
		</Bin>
		<Bin>
			<!--***** FISERV/MASTERCARD *******-->
			<idBin>103</idBin>
			<idAdquirente>2</idAdquirente>
			<nombreSello>MASTERCARD</nombreSello>
			<colBines>
				<rangoBin>
					<binDesde>100383</binDesde>
					<binHasta>100383</binHasta>
					<rangoExtDesde>000</rangoExtDesde>
					<rangoExtHasta>999</rangoExtHasta>
				</rangoBin>
				<rangoBin>
					<binDesde>201282</binDesde>
					<binHasta>201282</binHasta>
					<rangoExtDesde>000</rangoExtDesde>
					<rangoExtHasta>999</rangoExtHasta>
				</rangoBin>
				<rangoBin>
					<binDesde>308800</binDesde>
					<binHasta>309499</binHasta>
					<rangoExtDesde>000</rangoExtDesde>
					<rangoExtHasta>999</rangoExtHasta>
				</rangoBin>
				<rangoBin>
					<binDesde>309600</binDesde>
					<binHasta>310299</binHasta>
					<rangoExtDesde>000</rangoExtDesde>
					<rangoExtHasta>999</rangoExtHasta>
				</rangoBin>
				<rangoBin>
					<binDesde>311200</binDesde>
					<binHasta>312099</binHasta>
					<rangoExtDesde>000</rangoExtDesde>
					<rangoExtHasta>999</rangoExtHasta>
				</rangoBin>
				<rangoBin>
					<binDesde>315800</binDesde>
					<binHasta>315999</binHasta>
					<rangoExtDesde>000</rangoExtDesde>
					<rangoExtHasta>999</rangoExtHasta>
				</rangoBin>
				<rangoBin>
					<binDesde>333700</binDesde>
					<binHasta>334999</binHasta>
					<rangoExtDesde>000</rangoExtDesde>
					<rangoExtHasta>999</rangoExtHasta>
				</rangoBin>
				<rangoBin>
					<binDesde>352800</binDesde>
					<binHasta>358999</binHasta>
					<rangoExtDesde>000</rangoExtDesde>
					<rangoExtHasta>999</rangoExtHasta>
				</rangoBin>
				<rangoBin>
					<binDesde>510000</binDesde>
					<binHasta>569999</binHasta>
					<rangoExtDesde>000</rangoExtDesde>
					<rangoExtHasta>999</rangoExtHasta>
				</rangoBin>
				<rangoBin>
					<binDesde>222100</binDesde>
					<binHasta>272099</binHasta>
					<rangoExtDesde>000</rangoExtDesde>
					<rangoExtHasta>999</rangoExtHasta>
				</rangoBin>
			</colBines>
			<DL_FAST_CO>false</DL_FAST_CO>
			<DL_SDLCINT>ATW2X4S25=1&amp;D2%C0\N0+A8E=,,,1</DL_SDLCINT>
			<DL_SDLC_MOD>AT+MS=V22,0,300,1200,300,1200</DL_SDLC_MOD>
			<DL_SDLC_ON>true</DL_SDLC_ON>
			<DL_START>AT&amp;FE0Q0V0</DL_START>
			<afamSC>120</afamSC>
			<cifraCanalTLS>S</cifraCanalTLS>
			<colBinesAfam>0</colBinesAfam>
			<discretionaryAfam>0</discretionaryAfam>
			<iP>200.058.130.206</iP>
			<iP2>200.058.130.206</iP2>
			<iP3>200.058.130.206</iP3>
			<impCierreTotalesCero>N</impCierreTotalesCero>
			<ksi>0B0117</ksi>
			<largoBinesAfam>0</largoBinesAfam>
			<location>1</location>
			<msDukpt>D</msDukpt>
			<msgInicializacion>N</msgInicializacion>
			<nIi>0003</nIi>
			<operaCredito>L</operaCredito>
			<operaDebito>L</operaDebito>
			<operaOffLine>N</operaOffLine>
			<puerto>30215</puerto>
			<puerto2>30205</puerto2>
			<puerto3>30215</puerto3>
			<requiereCuotas>S</requiereCuotas>
			<requierePIN>N</requierePIN>
			<reversaDiferida>S</reversaDiferida>
			<telnac1>29031239</telnac1>
			<telnac2>22015946</telnac2>
			<telnac3>22015946</telnac3>
			<versionEMV>1</versionEMV>
		</Bin>
		<Bin>
			<!--***** FISERV/SODEXO *******-->
			<idBin>109</idBin>
			<idAdquirente>2</idAdquirente>
			<nombreSello>SODEXO</nombreSello>
			<colBines>
				<rangoBin>
					<binDesde>505864</binDesde>
					<binHasta>505865</binHasta>
					<rangoExtDesde>000</rangoExtDesde>
					<rangoExtHasta>999</rangoExtHasta>
				</rangoBin>
			</colBines>
			<DL_FAST_CO>false</DL_FAST_CO>
			<DL_SDLCINT>ATW2X4S25=1&amp;D2%C0\N0+A8E=,,,1</DL_SDLCINT>
			<DL_SDLC_MOD>AT+MS=V22,0,300,1200,300,1200</DL_SDLC_MOD>
			<DL_SDLC_ON>true</DL_SDLC_ON>
			<DL_START>AT&amp;FE0Q0V0</DL_START>
			<afamSC>120</afamSC>
			<cifraCanalTLS>S</cifraCanalTLS>
			<colBinesAfam>0</colBinesAfam>
			<discretionaryAfam>0</discretionaryAfam>
			<iP>200.058.130.206</iP>
			<iP2>200.058.130.206</iP2>
			<iP3>200.058.130.206</iP3>
			<impCierreTotalesCero>N</impCierreTotalesCero>
			<ksi>0B0117</ksi>
			<largoBinesAfam>0</largoBinesAfam>
			<location>1</location>
			<msDukpt>D</msDukpt>
			<msgInicializacion>N</msgInicializacion>
			<nIi>0003</nIi>
			<operaCredito>L</operaCredito>
			<operaDebito>L</operaDebito>
			<operaOffLine>N</operaOffLine>
			<puerto>30215</puerto>
			<puerto2>30205</puerto2>
			<puerto3>30215</puerto3>
			<requiereCuotas>N</requiereCuotas>
			<requierePIN>N</requierePIN>
			<reversaDiferida>S</reversaDiferida>
			<telnac1>29031239</telnac1>
			<telnac2>22015946</telnac2>
			<telnac3>22015946</telnac3>
			<versionEMV>1</versionEMV>
		</Bin>
		<Bin>
			<!--***** FISERV/LIDER AFAM *******-->
			<idBin>110</idBin>
			<idAdquirente>2</idAdquirente>
			<nombreSello>LIDER AFAM</nombreSello>
			<colBines>
				<rangoBin>
					<binDesde>501088</binDesde>
					<binHasta>501088</binHasta>
					<rangoExtDesde>000</rangoExtDesde>
					<rangoExtHasta>999</rangoExtHasta>
				</rangoBin>
			</colBines>
			<DL_FAST_CO>false</DL_FAST_CO>
			<DL_SDLCINT>ATW2X4S25=1&amp;D2%C0\N0+A8E=,,,1</DL_SDLCINT>
			<DL_SDLC_MOD>AT+MS=V22,0,300,1200,300,1200</DL_SDLC_MOD>
			<DL_SDLC_ON>true</DL_SDLC_ON>
			<DL_START>AT&amp;FE0Q0V0</DL_START>
			<afamSC>120</afamSC>
			<cifraCanalTLS>S</cifraCanalTLS>
			<colBinesAfam>501088-501088</colBinesAfam>
			<discretionaryAfam>0</discretionaryAfam>
			<iP>200.058.130.206</iP>
			<iP2>200.058.130.206</iP2>
			<iP3>200.058.130.206</iP3>
			<impCierreTotalesCero>N</impCierreTotalesCero>
			<ksi>0B0117</ksi>
			<largoBinesAfam>6</largoBinesAfam>
			<location>1</location>
			<msDukpt>D</msDukpt>
			<msgInicializacion>N</msgInicializacion>
			<nIi>0003</nIi>
			<operaCredito>L</operaCredito>
			<operaDebito>L</operaDebito>
			<operaOffLine>N</operaOffLine>
			<puerto>30215</puerto>
			<puerto2>30205</puerto2>
			<puerto3>30215</puerto3>
			<requiereCuotas>N</requiereCuotas>
			<requierePIN>N</requierePIN>
			<reversaDiferida>S</reversaDiferida>
			<telnac1>29031239</telnac1>
			<telnac2>22015946</telnac2>
			<telnac3>22015946</telnac3>
			<versionEMV>1</versionEMV>
		</Bin>
		<Bin>
			<!--***** FISERV/MAESTRO *******-->
			<idBin>102</idBin>
			<idAdquirente>2</idAdquirente>
			<nombreSello>MAESTRO</nombreSello>
			<colBines>
				<rangoBin>
					<binDesde>500000</binDesde>
					<binHasta>699999</binHasta>
					<rangoExtDesde>000</rangoExtDesde>
					<rangoExtHasta>999</rangoExtHasta>
				</rangoBin>
			</colBines>
			<DL_FAST_CO>false</DL_FAST_CO>
			<DL_SDLCINT>ATW2X4S25=1&amp;D2%C0\N0+A8E=,,,1</DL_SDLCINT>
			<DL_SDLC_MOD>AT+MS=V22,0,300,1200,300,1200</DL_SDLC_MOD>
			<DL_SDLC_ON>true</DL_SDLC_ON>
			<DL_START>AT&amp;FE0Q0V0</DL_START>
			<afamSC>999</afamSC>
			<cifraCanalTLS>S</cifraCanalTLS>
			<colBinesAfam>501071-501071*501074-501074</colBinesAfam>
			<discretionaryAfam>0</discretionaryAfam>
			<iP>200.058.130.206</iP>
			<iP2>200.058.130.206</iP2>
			<iP3>200.058.130.206</iP3>
			<impCierreTotalesCero>N</impCierreTotalesCero>
			<ksi>0B0117</ksi>
			<largoBinesAfam>6</largoBinesAfam>
			<location>1</location>
			<msDukpt>D</msDukpt>
			<msgInicializacion>N</msgInicializacion>
			<nIi>0003</nIi>
			<operaCredito>N</operaCredito>
			<operaDebito>L</operaDebito>
			<operaOffLine>N</operaOffLine>
			<puerto>30215</puerto>
			<puerto2>30205</puerto2>
			<puerto3>30215</puerto3>
			<requiereCuotas>N</requiereCuotas>
			<requierePIN>S</requierePIN>
			<reversaDiferida>S</reversaDiferida>
			<telnac1>29031239</telnac1>
			<telnac2>22015946</telnac2>
			<telnac3>22015946</telnac3>
			<versionEMV>1</versionEMV>
		</Bin>
	</BaseBin>
	<BaseTerminalComercio>
		<Terminal>
			<!--OCA S.A./OCA (3/1)-->
			<activoSN>S</activoSN>
			<idTerminal>74196598</idTerminal>
			<nombre>NEMESIS</nombre>
			<direccion>CHUCARRO 1146</direccion>
			<telefono>27076442</telefono>
			<rut>218076280018</rut>
			<idBin>1</idBin>
			<modoConexion>E</modoConexion>
			<nroSerie>261-959-275</nroSerie>
			<did>037AC</did>
			<iva>22</iva>
			<nroComercio>141407</nroComercio>
			<nroComercioCierre>141407</nroComercioCierre>
			<nroComercioDolares>0</nroComercioDolares>
			<plan>0</plan>
			<propina>S</propina>
			<reqCVV>N</reqCVV>
			<reqDocumento>S</reqDocumento>
			<reqUlt4Dig>N</reqUlt4Dig>
			<nroTerminal>30200001</nroTerminal>
			<indi>6</indi>
			<codRamo>C</codRamo>
			<tipoMayorista>N</tipoMayorista>
		</Terminal>
		<Terminal>
			<!--VISANET/VISA (4/2)-->
			<activoSN>S</activoSN>
			<idTerminal>74196598</idTerminal>
			<nombre>NEMESIS</nombre>
			<direccion>CHUCARRO 1146</direccion>
			<telefono>27076442</telefono>
			<rut>218076280018</rut>
			<idBin>2</idBin>
			<modoConexion>E</modoConexion>
			<nroSerie>261-959-275</nroSerie>
			<did>04CB4</did>
			<iva>22</iva>
			<nroComercio>02081903001</nroComercio>
			<nroComercioCierre>02081903001</nroComercioCierre>
			<nroComercioDolares>0</nroComercioDolares>
			<plan>0</plan>
			<propina>N</propina>
			<reqCVV>N</reqCVV>
			<reqDocumento>N</reqDocumento>
			<reqUlt4Dig>N</reqUlt4Dig>
			<nroTerminal>30200001</nroTerminal>
			<indi>6</indi>
			<codRamo>C</codRamo>
			<tipoMayorista>N</tipoMayorista>
		</Terminal>
		<Terminal>
			<!--CABAL/CABAL CREDITO (1/7)-->
			<activoSN>S</activoSN>
			<idTerminal>74196598</idTerminal>
			<nombre>NEMESIS</nombre>
			<direccion>CHUCARRO 1146</direccion>
			<telefono>27076442</telefono>
			<rut>218076280018</rut>
			<idBin>7</idBin>
			<modoConexion>E</modoConexion>
			<nroSerie>261-959-275</nroSerie>
			<did>04CB4</did>
			<iva>22</iva>
			<nroComercio>06100004012</nroComercio>
			<nroComercioCierre>06100004012</nroComercioCierre>
			<nroComercioDolares>06100004012</nroComercioDolares>
			<plan>0</plan>
			<propina>N</propina>
			<reqCVV>N</reqCVV>
			<reqDocumento>N</reqDocumento>
			<reqUlt4Dig>N</reqUlt4Dig>
			<nroTerminal>30200001</nroTerminal>
			<indi>6</indi>
			<codRamo>C</codRamo>
			<tipoMayorista>N</tipoMayorista>
		</Terminal>
		<Terminal>
			<!--EDENRED/CABAL EDENRED (21/8)-->
			<activoSN>N</activoSN>
			<idTerminal>74196598</idTerminal>
			<nombre>NEMESIS</nombre>
			<direccion>CHUCARRO 1146</direccion>
			<telefono>27076442</telefono>
			<rut>218076280018</rut>
			<idBin>8</idBin>
			<modoConexion>E</modoConexion>
			<nroSerie>261-959-275</nroSerie>
			<did>04CB4</did>
			<iva>22</iva>
			<nroComercio>0</nroComercio>
			<nroComercioCierre>0</nroComercioCierre>
			<nroComercioDolares>0</nroComercioDolares>
			<plan>0</plan>
			<propina>N</propina>
			<reqCVV>N</reqCVV>
			<reqDocumento>N</reqDocumento>
			<reqUlt4Dig>N</reqUlt4Dig>
			<nroTerminal>30200001</nroTerminal>
			<indi>6</indi>
			<codRamo>C</codRamo>
			<tipoMayorista>N</tipoMayorista>
		</Terminal>
		<Terminal>
			<!--CLUB DEL ESTE/CLUB DEL ESTE (14/14)-->
			<activoSN>N</activoSN>
			<idTerminal>74196598</idTerminal>
			<nombre>NEMESIS</nombre>
			<direccion>CHUCARRO 1146</direccion>
			<telefono>27076442</telefono>
			<rut>218076280018</rut>
			<idBin>14</idBin>
			<modoConexion>E</modoConexion>
			<nroSerie>261-959-275</nroSerie>
			<did>04CB4</did>
			<iva>22</iva>
			<nroComercio>0</nroComercio>
			<nroComercioCierre>0</nroComercioCierre>
			<nroComercioDolares>0</nroComercioDolares>
			<plan>0</plan>
			<propina>N</propina>
			<reqCVV>N</reqCVV>
			<reqDocumento>N</reqDocumento>
			<reqUlt4Dig>N</reqUlt4Dig>
			<nroTerminal>30200001</nroTerminal>
			<indi>6</indi>
			<codRamo>C</codRamo>
			<tipoMayorista>N</tipoMayorista>
		</Terminal>
		<Terminal>
			<!--ANDA/ANDA (12/30)-->
			<activoSN>N</activoSN>
			<idTerminal>74196598</idTerminal>
			<nombre>NEMESIS</nombre>
			<direccion>CHUCARRO 1146</direccion>
			<telefono>27076442</telefono>
			<rut>218076280018</rut>
			<idBin>30</idBin>
			<modoConexion>E</modoConexion>
			<nroSerie>261-959-275</nroSerie>
			<did>04CB4</did>
			<iva>22</iva>
			<nroComercio>0</nroComercio>
			<nroComercioCierre>0</nroComercioCierre>
			<nroComercioDolares>0</nroComercioDolares>
			<plan>0</plan>
			<propina>N</propina>
			<reqCVV>N</reqCVV>
			<reqDocumento>N</reqDocumento>
			<reqUlt4Dig>N</reqUlt4Dig>
			<nroTerminal>30200001</nroTerminal>
			<indi>6</indi>
			<codRamo>C</codRamo>
			<tipoMayorista>N</tipoMayorista>
		</Terminal>
		<Terminal>
			<!--AMEX/AMEX (5/37)-->
			<activoSN>S</activoSN>
			<idTerminal>74196598</idTerminal>
			<nombre>NEMESIS</nombre>
			<direccion>CHUCARRO 1146</direccion>
			<telefono>27076442</telefono>
			<rut>218076280018</rut>
			<idBin>37</idBin>
			<modoConexion>E</modoConexion>
			<nroSerie>261-959-275</nroSerie>
			<did>04CB4</did>
			<iva>22</iva>
			<nroComercio>9960346567</nroComercio>
			<nroComercioCierre>9960346567</nroComercioCierre>
			<nroComercioDolares>0</nroComercioDolares>
			<plan>0</plan>
			<propina>N</propina>
			<reqCVV>N</reqCVV>
			<reqDocumento>N</reqDocumento>
			<reqUlt4Dig>N</reqUlt4Dig>
			<nroTerminal>30200001</nroTerminal>
			<indi>6</indi>
			<codRamo>C</codRamo>
			<tipoMayorista>N</tipoMayorista>
		</Terminal>
		<Terminal>
			<!--PASSCARD/PASSCARD (10/50)-->
			<activoSN>N</activoSN>
			<idTerminal>74196598</idTerminal>
			<nombre>NEMESIS</nombre>
			<direccion>CHUCARRO 1146</direccion>
			<telefono>27076442</telefono>
			<rut>218076280018</rut>
			<idBin>50</idBin>
			<modoConexion>E</modoConexion>
			<nroSerie>261-959-275</nroSerie>
			<did>04CB4</did>
			<iva>22</iva>
			<nroComercio>0</nroComercio>
			<nroComercioCierre>0</nroComercioCierre>
			<nroComercioDolares>0</nroComercioDolares>
			<plan>0</plan>
			<propina>N</propina>
			<reqCVV>N</reqCVV>
			<reqDocumento>N</reqDocumento>
			<reqUlt4Dig>N</reqUlt4Dig>
			<nroTerminal>30200001</nroTerminal>
			<indi>6</indi>
			<codRamo>C</codRamo>
			<tipoMayorista>N</tipoMayorista>
		</Terminal>
		<Terminal>
			<!--CREDITOS D/TARJETA D (600/51)-->
			<activoSN>S</activoSN>
			<idTerminal>74196598</idTerminal>
			<nombre>NEMESIS</nombre>
			<direccion>CHUCARRO 1146</direccion>
			<telefono>27076442</telefono>
			<rut>218076280018</rut>
			<idBin>51</idBin>
			<modoConexion>E</modoConexion>
			<nroSerie>261-959-275</nroSerie>
			<did>04CB4</did>
			<iva>22</iva>
			<nroComercio>073339</nroComercio>
			<nroComercioCierre>073339</nroComercioCierre>
			<nroComercioDolares>073339</nroComercioDolares>
			<plan>0</plan>
			<propina>N</propina>
			<reqCVV>N</reqCVV>
			<reqDocumento>N</reqDocumento>
			<reqUlt4Dig>N</reqUlt4Dig>
			<nroTerminal>30200001</nroTerminal>
			<indi>6</indi>
			<codRamo>C</codRamo>
			<tipoMayorista>N</tipoMayorista>
		</Terminal>
		<Terminal>
			<!--MIDES/MIDES (13/70)-->
			<activoSN>N</activoSN>
			<idTerminal>74196598</idTerminal>
			<nombre>NEMESIS</nombre>
			<direccion>CHUCARRO 1146</direccion>
			<telefono>27076442</telefono>
			<rut>218076280018</rut>
			<idBin>70</idBin>
			<modoConexion>E</modoConexion>
			<nroSerie>261-959-275</nroSerie>
			<did>04CB4</did>
			<iva>22</iva>
			<nroComercio>0</nroComercio>
			<nroComercioCierre>0</nroComercioCierre>
			<nroComercioDolares>0</nroComercioDolares>
			<plan>0</plan>
			<propina>N</propina>
			<reqCVV>N</reqCVV>
			<reqDocumento>S</reqDocumento>
			<reqUlt4Dig>N</reqUlt4Dig>
			<nroTerminal>30200001</nroTerminal>
			<indi>3</indi>
			<codRamo>C</codRamo>
			<tipoMayorista>N</tipoMayorista>
		</Terminal>
		<Terminal>
			<!--CABAL/CABAL AFAM (1/776)-->
			<activoSN>S</activoSN>
			<idTerminal>74196598</idTerminal>
			<nombre>NEMESIS</nombre>
			<direccion>CHUCARRO 1146</direccion>
			<telefono>27076442</telefono>
			<rut>218076280018</rut>
			<idBin>776</idBin>
			<modoConexion>E</modoConexion>
			<nroSerie>261-959-275</nroSerie>
			<did>04CB4</did>
			<iva>22</iva>
			<nroComercio>06100004012</nroComercio>
			<nroComercioCierre>06100004012</nroComercioCierre>
			<nroComercioDolares>06100004012</nroComercioDolares>
			<plan>0</plan>
			<propina>N</propina>
			<reqCVV>N</reqCVV>
			<reqDocumento>N</reqDocumento>
			<reqUlt4Dig>N</reqUlt4Dig>
			<nroTerminal>30200001</nroTerminal>
			<indi>6</indi>
			<codRamo>C</codRamo>
			<tipoMayorista>N</tipoMayorista>
		</Terminal>
		<Terminal>
			<!--CABAL/CABAL DEBITO (1/777)-->
			<activoSN>S</activoSN>
			<idTerminal>74196598</idTerminal>
			<nombre>NEMESIS</nombre>
			<direccion>CHUCARRO 1146</direccion>
			<telefono>27076442</telefono>
			<rut>218076280018</rut>
			<idBin>777</idBin>
			<modoConexion>E</modoConexion>
			<nroSerie>261-959-275</nroSerie>
			<did>04CB4</did>
			<iva>22</iva>
			<nroComercio>06100004012</nroComercio>
			<nroComercioCierre>06100004012</nroComercioCierre>
			<nroComercioDolares>06100004012</nroComercioDolares>
			<plan>0</plan>
			<propina>N</propina>
			<reqCVV>N</reqCVV>
			<reqDocumento>N</reqDocumento>
			<reqUlt4Dig>N</reqUlt4Dig>
			<nroTerminal>30200001</nroTerminal>
			<indi>6</indi>
			<codRamo>C</codRamo>
			<tipoMayorista>N</tipoMayorista>
		</Terminal>
		<Terminal>
			<!--CABAL/BENEFICIOS (1/778)-->
			<activoSN>N</activoSN>
			<idTerminal>74196598</idTerminal>
			<nombre>NEMESIS</nombre>
			<direccion>CHUCARRO 1146</direccion>
			<telefono>27076442</telefono>
			<rut>218076280018</rut>
			<idBin>778</idBin>
			<modoConexion>E</modoConexion>
			<nroSerie>261-959-275</nroSerie>
			<did>04CB4</did>
			<iva>22</iva>
			<nroComercio>0</nroComercio>
			<nroComercioCierre>0</nroComercioCierre>
			<nroComercioDolares>0</nroComercioDolares>
			<plan>0</plan>
			<propina>N</propina>
			<reqCVV>N</reqCVV>
			<reqDocumento>N</reqDocumento>
			<reqUlt4Dig>N</reqUlt4Dig>
			<nroTerminal>30200001</nroTerminal>
			<indi>6</indi>
			<codRamo>C</codRamo>
			<tipoMayorista>N</tipoMayorista>
		</Terminal>
		<Terminal>
			<!--CREDITEL/CREDITEL (11/800)-->
			<activoSN>N</activoSN>
			<idTerminal>74196598</idTerminal>
			<nombre>NEMESIS</nombre>
			<direccion>CHUCARRO 1146</direccion>
			<telefono>27076442</telefono>
			<rut>218076280018</rut>
			<idBin>800</idBin>
			<modoConexion>E</modoConexion>
			<nroSerie>261-959-275</nroSerie>
			<did>04CB4</did>
			<iva>22</iva>
			<nroComercio>0</nroComercio>
			<nroComercioCierre>0</nroComercioCierre>
			<nroComercioDolares>0</nroComercioDolares>
			<plan>0</plan>
			<propina>N</propina>
			<reqCVV>N</reqCVV>
			<reqDocumento>N</reqDocumento>
			<reqUlt4Dig>N</reqUlt4Dig>
			<nroTerminal>30200001</nroTerminal>
			<indi>6</indi>
			<codRamo>C</codRamo>
			<tipoMayorista>N</tipoMayorista>
		</Terminal>
		<Terminal>
			<!--FISERV/LIDER (2/101)-->
			<activoSN>A</activoSN>
			<idTerminal>74196598</idTerminal>
			<nombre>NEMESIS</nombre>
			<direccion>CHUCARRO 1146</direccion>
			<telefono>27076442</telefono>
			<rut>218076280018</rut>
			<idBin>101</idBin>
			<modoConexion>E</modoConexion>
			<nroSerie>261-959-275</nroSerie>
			<did>026D2</did>
			<iva>22</iva>
			<nroComercio>22542950</nroComercio>
			<nroComercioCierre>22542950</nroComercioCierre>
			<nroComercioDolares>0</nroComercioDolares>
			<plan>0</plan>
			<propina>N</propina>
			<reqCVV>N</reqCVV>
			<reqDocumento>N</reqDocumento>
			<reqUlt4Dig>N</reqUlt4Dig>
			<nroTerminal>30200001</nroTerminal>
			<indi>6</indi>
			<codRamo>C</codRamo>
			<tipoMayorista>N</tipoMayorista>
		</Terminal>
		<Terminal>
			<!--FISERV/MASTERCARD (2/103)-->
			<activoSN>A</activoSN>
			<idTerminal>74196598</idTerminal>
			<nombre>NEMESIS</nombre>
			<direccion>CHUCARRO 1146</direccion>
			<telefono>27076442</telefono>
			<rut>218076280018</rut>
			<idBin>103</idBin>
			<modoConexion>E</modoConexion>
			<nroSerie>261-959-275</nroSerie>
			<did>026D2</did>
			<iva>22</iva>
			<nroComercio>22542950</nroComercio>
			<nroComercioCierre>22542950</nroComercioCierre>
			<nroComercioDolares>0</nroComercioDolares>
			<plan>0</plan>
			<propina>N</propina>
			<reqCVV>N</reqCVV>
			<reqDocumento>N</reqDocumento>
			<reqUlt4Dig>N</reqUlt4Dig>
			<nroTerminal>30200001</nroTerminal>
			<indi>6</indi>
			<codRamo>C</codRamo>
			<tipoMayorista>N</tipoMayorista>
		</Terminal>
		<Terminal>
			<!--FISERV/SODEXO (2/109)-->
			<activoSN>N</activoSN>
			<idTerminal>74196598</idTerminal>
			<nombre>NEMESIS</nombre>
			<direccion>CHUCARRO 1146</direccion>
			<telefono>27076442</telefono>
			<rut>218076280018</rut>
			<idBin>109</idBin>
			<modoConexion>E</modoConexion>
			<nroSerie>261-959-275</nroSerie>
			<did>026D2</did>
			<iva>22</iva>
			<nroComercio>0</nroComercio>
			<nroComercioCierre>0</nroComercioCierre>
			<nroComercioDolares>0</nroComercioDolares>
			<plan>0</plan>
			<propina>N</propina>
			<reqCVV>N</reqCVV>
			<reqDocumento>N</reqDocumento>
			<reqUlt4Dig>N</reqUlt4Dig>
			<nroTerminal>30200001</nroTerminal>
			<indi>6</indi>
			<codRamo>C</codRamo>
			<tipoMayorista>N</tipoMayorista>
		</Terminal>
		<Terminal>
			<!--FISERV/LIDER AFAM (2/110)-->
			<activoSN>A</activoSN>
			<idTerminal>74196598</idTerminal>
			<nombre>NEMESIS</nombre>
			<direccion>CHUCARRO 1146</direccion>
			<telefono>27076442</telefono>
			<rut>218076280018</rut>
			<idBin>110</idBin>
			<modoConexion>E</modoConexion>
			<nroSerie>261-959-275</nroSerie>
			<did>026D2</did>
			<iva>22</iva>
			<nroComercio>22542950</nroComercio>
			<nroComercioCierre>22542950</nroComercioCierre>
			<nroComercioDolares>0</nroComercioDolares>
			<plan>0</plan>
			<propina>N</propina>
			<reqCVV>N</reqCVV>
			<reqDocumento>N</reqDocumento>
			<reqUlt4Dig>N</reqUlt4Dig>
			<nroTerminal>30200001</nroTerminal>
			<indi>6</indi>
			<codRamo>C</codRamo>
			<tipoMayorista>N</tipoMayorista>
		</Terminal>
		<Terminal>
			<!--FISERV/MAESTRO (2/102)-->
			<activoSN>A</activoSN>
			<idTerminal>74196598</idTerminal>
			<nombre>NEMESIS</nombre>
			<direccion>CHUCARRO 1146</direccion>
			<telefono>27076442</telefono>
			<rut>218076280018</rut>
			<idBin>102</idBin>
			<modoConexion>E</modoConexion>
			<nroSerie>261-959-275</nroSerie>
			<did>026D2</did>
			<iva>22</iva>
			<nroComercio>22542950</nroComercio>
			<nroComercioCierre>22542950</nroComercioCierre>
			<nroComercioDolares>0</nroComercioDolares>
			<plan>0</plan>
			<propina>N</propina>
			<reqCVV>N</reqCVV>
			<reqDocumento>N</reqDocumento>
			<reqUlt4Dig>N</reqUlt4Dig>
			<nroTerminal>30200001</nroTerminal>
			<indi>6</indi>
			<codRamo>C</codRamo>
			<tipoMayorista>N</tipoMayorista>
		</Terminal>
	</BaseTerminalComercio>
	<BaseTerminalComercioMayorista>
	</BaseTerminalComercioMayorista>
</Inicializacion>
